gsbatch/__init__.py
gsbatch/_version.py
gsbatch/external.py
gsbatch/path.py
gsbatch/rich.py
gsbatch/cli/__init__.py
gsbatch/cli/gsbatch_topng.py
gsbatch-0.1.0.dist-info/LICENSE
gsbatch-0.1.0.dist-info/METADATA
gsbatch-0.1.0.dist-info/WHEEL
gsbatch-0.1.0.dist-info/entry_points.txt
gsbatch-0.1.0.dist-info/top_level.txt
gsbatch-0.1.0.dist-info/RECORD
