Metadata-Version: 2.1
Name: gsbatch
Version: 0.1.0
Summary: Apply GhostScript to a batch of files
Home-page: https://github.com/tdegeus/gsbatch
Author: Tom de Geus
Author-email: tom@geus.me
License: MIT
Keywords: YAML,Bash
Platform: UNKNOWN
Requires-Dist: click
